README.md
setup.py
cluster_drug_discovery/__init__.py
cluster_drug_discovery/main.py
cluster_drug_discovery.egg-info/PKG-INFO
cluster_drug_discovery.egg-info/SOURCES.txt
cluster_drug_discovery.egg-info/dependency_links.txt
cluster_drug_discovery.egg-info/top_level.txt
cluster_drug_discovery/analysis/__init__.py
cluster_drug_discovery/analysis/metrics.py
cluster_drug_discovery/dimensionallity/__init__.py
cluster_drug_discovery/dimensionallity/reduction.py
cluster_drug_discovery/helpers/__init__.py
cluster_drug_discovery/helpers/helpers.py
cluster_drug_discovery/input_preprocess/__init__.py
cluster_drug_discovery/input_preprocess/coords_extract.py
cluster_drug_discovery/input_preprocess/dihedral_extract.py
cluster_drug_discovery/input_preprocess/dihedrals.extract.py
cluster_drug_discovery/input_preprocess/feature_extraction.py
cluster_drug_discovery/input_preprocess/point.py
cluster_drug_discovery/methods/__init__.py
cluster_drug_discovery/methods/agglomerative.py
cluster_drug_discovery/methods/clusterclass.py
cluster_drug_discovery/methods/dbscan.py
cluster_drug_discovery/methods/hdbscan.py
cluster_drug_discovery/methods/kmeans.py
cluster_drug_discovery/visualization/__init__.py
cluster_drug_discovery/visualization/plots.py