Metadata-Version: 1.0
Name: cluster-drug-discovery
Version: 1.0.0.0
Summary: Clustering methodologies over pdb trajectories
Home-page: https://github.com/NostrumBioDiscovery/cluster_drug_discovery
Author: Daniel Soler
Author-email: daniel.soler@nostrumbiodiscovery.com
License: MIT
Platform: UNKNOWN
